srtfix/__init__.py
srtfix/data.py
srtfix/srtfix.py
srtfix/test_srtfix.py
srtfix/test_text.py
srtfix/text.py
srtfix-0.0.1.dist-info/LICENSE
srtfix-0.0.1.dist-info/METADATA
srtfix-0.0.1.dist-info/WHEEL
srtfix-0.0.1.dist-info/entry_points.txt
srtfix-0.0.1.dist-info/top_level.txt
srtfix-0.0.1.dist-info/RECORD
