Metadata-Version: 2.1
Name: srtfix
Version: 0.0.1
Summary: A tool to rename srt files
Home-page: https://github.com/srtfix/srtfix
Author: Gilad Kutiel
Author-email: gilad.kutiel@gmail.com
License: UNKNOWN
Platform: UNKNOWN
Classifier: Programming Language :: Python :: 3
Classifier: License :: OSI Approved :: MIT License
Classifier: Operating System :: OS Independent
Requires-Python: >=3.6
